{
    "document":{
        "file_hash":"55001411f34117251a51a954e8528be3bf3dfca8",
        "annotations":[],
        "description":"",
        "language":"eng",
        "title":"Code Minier Amend\u00e9",
        "data":{},
        "created_at":"Tue, 06 Aug 2013 23:12:11 +0000",
        "display_language":"eng",
        "updated_at":"Mon, 29 Dec 2014 09:06:57 +0000",
        "id":"748592-code-minier-amende",
        "access":"public",
        "source":"",
        "resources":{
            "search":"https://www.documentcloud.org/documents/748592/search.json?q={query}",
            "text":"https://s3.amazonaws.com/s3.documentcloud.org/documents/748592/code-minier-amende.txt",
            "translations_url":"https://www.documentcloud.org/translations/{realm}/{language}",
            "page":{
                "text":"https://www.documentcloud.org/documents/748592/pages/code-minier-amende-p{page}.txt",
                "image":"https://s3.amazonaws.com/s3.documentcloud.org/documents/748592/pages/code-minier-amende-p{page}-{size}.gif"
            },
            "pdf":"https://s3.amazonaws.com/s3.documentcloud.org/documents/748592/code-minier-amende.pdf",
            "thumbnail":"https://s3.amazonaws.com/s3.documentcloud.org/documents/748592/pages/code-minier-amende-p1-thumbnail.gif",
            "print_annotations":"https://www.documentcloud.org/notes/print?docs[]=748592"
        },
        "contributor":"Jed Miller",
        "contributor_organization":"Revue des Conventions Miniers",
        "sections":[],
        "pages":182,
        "canonical_url":"http://www.documentcloud.org/documents/748592-code-minier-amende.html"
    }
}