{"annotation":{"company":["Sannati Agro Farm Enterprises Pvt. Ltd (Ethiopia Branch)","Sannati Agro Farm Enterprises Plc","Pradeep Mammemela",null],"type_of_contract":["Land lease agreement"],"project_title":[null],"license_concession_name":[null],"government_entities":["The Ministry of Agriculture and Rural Development"],"signature_date":["10-04-10"],"signature_year":[2010]},"metadata":{"country":"Ethiopia","resource":"Rice and rotational pulse and cereal crops","type_of_contract":"Land lease agreement","signature_date":"10-04-10","signature_year":2010},"contract_name":"Sannati%20Agro%20Farm%20Enterprises_Ethiopia.xlsx","file_name":"Sannati%20Agro%20Farm%20Enterprises_Ethiopia.xlsx","pdf_url":"https:\/\/www.dropbox.com\/s\/t358g7kgionm4if\/Sannati%20%28Indian%20invest%20-%20rice%20etc%202010%29.pdf"}